fds/__init__.py
fds/sdk/__init__.py
fds/sdk/OpenRisk/__init__.py
fds/sdk/OpenRisk/api_client.py
fds/sdk/OpenRisk/configuration.py
fds/sdk/OpenRisk/exceptions.py
fds/sdk/OpenRisk/model_utils.py
fds/sdk/OpenRisk/rest.py
fds/sdk/OpenRisk/api/__init__.py
fds/sdk/OpenRisk/api/about_api.py
fds/sdk/OpenRisk/api/operations_api.py
fds/sdk/OpenRisk/apis/__init__.py
fds/sdk/OpenRisk/model/__init__.py
fds/sdk/OpenRisk/model/additional_calculation_inputs.py
fds/sdk/OpenRisk/model/additional_calculation_inputs_market_excess.py
fds/sdk/OpenRisk/model/asset_types.py
fds/sdk/OpenRisk/model/calculate_from_holdings_request_body.py
fds/sdk/OpenRisk/model/calculate_from_holdings_request_data.py
fds/sdk/OpenRisk/model/calendar_code.py
fds/sdk/OpenRisk/model/composite_asset_definitions.py
fds/sdk/OpenRisk/model/covariance_date_format_convention.py
fds/sdk/OpenRisk/model/currency_iso_code.py
fds/sdk/OpenRisk/model/error_item.py
fds/sdk/OpenRisk/model/error_response.py
fds/sdk/OpenRisk/model/exposure_date_format_convention.py
fds/sdk/OpenRisk/model/factor_group.py
fds/sdk/OpenRisk/model/factor_group_nodes.py
fds/sdk/OpenRisk/model/factors_visible.py
fds/sdk/OpenRisk/model/generate_id_mapping_request_body.py
fds/sdk/OpenRisk/model/generate_id_mapping_request_data.py
fds/sdk/OpenRisk/model/groups_labels.py
fds/sdk/OpenRisk/model/holding.py
fds/sdk/OpenRisk/model/holding_all_of.py
fds/sdk/OpenRisk/model/holdings.py
fds/sdk/OpenRisk/model/ids_and_market_values.py
fds/sdk/OpenRisk/model/inline_response200.py
fds/sdk/OpenRisk/model/inline_response2001.py
fds/sdk/OpenRisk/model/inline_response2001_data.py
fds/sdk/OpenRisk/model/inline_response2002.py
fds/sdk/OpenRisk/model/inline_response2003.py
fds/sdk/OpenRisk/model/inline_response2004.py
fds/sdk/OpenRisk/model/inline_response403.py
fds/sdk/OpenRisk/model/inline_response404.py
fds/sdk/OpenRisk/model/input_date.py
fds/sdk/OpenRisk/model/input_to_result_security_index_mapping.py
fds/sdk/OpenRisk/model/labels.py
fds.sdk.OpenRisk-4.0.3.dist-info/LICENSE
fds.sdk.OpenRisk-4.0.3.dist-info/METADATA
fds.sdk.OpenRisk-4.0.3.dist-info/WHEEL
fds.sdk.OpenRisk-4.0.3.dist-info/top_level.txt
fds.sdk.OpenRisk-4.0.3.dist-info/RECORD
